pg_sync_roles.py
pg_sync_roles-0.51.dist-info/METADATA
pg_sync_roles-0.51.dist-info/WHEEL
pg_sync_roles-0.51.dist-info/licenses/LICENSE
pg_sync_roles-0.51.dist-info/RECORD
