Metadata-Version: 2.4
Name: pg-sync-roles
Version: 0.51
Summary: Python utility function to ensure that a PostgreSQL role has certain permissions or role memberships
Project-URL: Source, https://github.com/uktrade/pg-sync-roles
Author-email: Department for Business and Trade <sre@digital.trade.gov.uk>
License-File: LICENSE
Classifier: License :: OSI Approved :: MIT License
Classifier: Operating System :: OS Independent
Classifier: Programming Language :: Python :: 3
Requires-Python: >=3.7
Requires-Dist: sqlalchemy>=1.4.24
Provides-Extra: ci
Requires-Dist: pytest-cov; extra == 'ci'
Requires-Dist: pytest==7.4.4; extra == 'ci'
Requires-Dist: wrapt==1.14.1; extra == 'ci'
Provides-Extra: ci-psycopg2-9-10-sqlalchemy1
Requires-Dist: psycopg2==2.9.10; extra == 'ci-psycopg2-9-10-sqlalchemy1'
Requires-Dist: sqlalchemy==1.4.24; extra == 'ci-psycopg2-9-10-sqlalchemy1'
Provides-Extra: ci-psycopg2-9-10-sqlalchemy2-0-31
Requires-Dist: psycopg2==2.9.10; extra == 'ci-psycopg2-9-10-sqlalchemy2-0-31'
Requires-Dist: sqlalchemy==2.0.31; extra == 'ci-psycopg2-9-10-sqlalchemy2-0-31'
Provides-Extra: ci-psycopg2-sqlalchemy1
Requires-Dist: psycopg2==2.9.2; extra == 'ci-psycopg2-sqlalchemy1'
Requires-Dist: sqlalchemy==1.4.24; extra == 'ci-psycopg2-sqlalchemy1'
Provides-Extra: ci-psycopg2-sqlalchemy2
Requires-Dist: psycopg2==2.9.2; extra == 'ci-psycopg2-sqlalchemy2'
Requires-Dist: sqlalchemy==2.0.0; extra == 'ci-psycopg2-sqlalchemy2'
Provides-Extra: ci-psycopg3-sqlalchemy2
Requires-Dist: psycopg==3.1.4; extra == 'ci-psycopg3-sqlalchemy2'
Requires-Dist: sqlalchemy==2.0.0; extra == 'ci-psycopg3-sqlalchemy2'
Provides-Extra: ci-psycopg3-sqlalchemy2-0-31
Requires-Dist: psycopg==3.1.4; extra == 'ci-psycopg3-sqlalchemy2-0-31'
Requires-Dist: sqlalchemy==2.0.31; extra == 'ci-psycopg3-sqlalchemy2-0-31'
Provides-Extra: dev
Requires-Dist: pytest>=7.4.4; extra == 'dev'
Requires-Dist: wrapt>=1.4.1; extra == 'dev'
